FYP_FPGA/TestBench/Read_weightbias/tb/Read_weightnbais_TB.v
`timescale 1 ns / 1 ps

module Read_weightnbais_TB ();

//************************Do Not Remove************************//
	initial begin
		$dumpfile("Read_weightnbais_TB.vcd");
		$dumpvars();
	end
//*************************************************************//

reg [15:0]t0,t1,t2,t3,t4;
reg [15:0]c1_w[0:5][0:0][4:0][4:0];
reg [15:0]c1_b[0:5];
reg [15:0]c3_w[0:15][5:0][4:0][4:0];
reg [15:0]c3_b[0:15];

initial begin
	#0
	$readmemh ("D:/FYP/FYP/weights/c1_weight.txt", c1_w);
    $readmemh ("D:/FYP/FYP/weights/c1_bias.txt", c1_b);
    $readmemh ("D:/FYP/FYP/weights/c3_weight.txt", c3_w);
    $readmemh ("D:/FYP/FYP/weights/c3_bias.txt", c3_b);
	t0 = 0;
	t1 = 0;
	t2 = 0;
	t3 = 0;
	t4 = 0;
	//c1_w*************
	#1
	t0 = c1_w[0][0][0][0];
	t1 = c1_w[0][0][1][1];
	t2 = c1_w[0][0][2][2];
	t3 = c1_w[0][0][3][3];
	t4 = c1_w[0][0][4][4];
	#1
	t0 = c1_w[1][0][0][0];
	t1 = c1_w[1][0][1][1];
	t2 = c1_w[1][0][2][2];
	t3 = c1_w[1][0][3][3];
	t4 = c1_w[1][0][4][4];
	#1
	t0 = c1_w[5][0][0][0];
	t1 = c1_w[5][0][1][1];
	t2 = c1_w[5][0][2][2];
	t3 = c1_w[5][0][3][3];
	t4 = c1_w[5][0][4][4];
	//***********************

	//c1_b*****************
	#1
	t0 = c1_b[0];
	t1 = c1_b[1];
	t2 = c1_b[3];
	t3 = c1_b[4];
	t4 = c1_b[5];
	//************************

	//c3_w*****************
	#1
	t0 = c3_w[0][0][0][0];
	t1 = c3_w[0][0][1][1];
	t2 = c3_w[0][0][2][2];
	t3 = c3_w[0][0][3][3];
	t4 = c3_w[0][0][4][4];
	#1
	t0 = c3_w[0][5][0][0];
	t1 = c3_w[0][5][1][1];
	t2 = c3_w[0][5][2][2];
	t3 = c3_w[0][5][3][3];
	t4 = c3_w[0][5][4][4];
	#1
	t0 = c3_w[1][0][0][0];
	t1 = c3_w[1][0][1][1];
	t2 = c3_w[1][0][2][2];
	t3 = c3_w[1][0][3][3];
	t4 = c3_w[1][0][4][4];	
	#1
	t0 = c3_w[1][5][0][0];
	t1 = c3_w[1][5][1][1];
	t2 = c3_w[1][5][2][2];
	t3 = c3_w[1][5][3][3];
	t4 = c3_w[1][5][4][4];
	#1
	t0 = c3_w[15][0][0][0];
	t1 = c3_w[15][0][1][1];
	t2 = c3_w[15][0][2][2];
	t3 = c3_w[15][0][3][3];
	t4 = c3_w[15][0][4][4];	
	#1
	t0 = c3_w[15][5][0][0];
	t1 = c3_w[15][5][1][1];
	t2 = c3_w[15][5][2][2];
	t3 = c3_w[15][5][3][3];
	t4 = c3_w[15][5][4][4];
	//************************

	//c3_b*****************
	#1
	t0 = c3_b[0];
	t1 = c3_b[4];
	t2 = c3_b[8];
	t3 = c3_b[11];
	t4 = c3_b[15];
	//************************

	#1
	$finish();
end

endmodule

FYP_FPGA/TestBench/Read_weightbias/Read_weightnbais_TB.vcd
$date
	Wed May 22 04:03:26 2024
$end
$version
	Icarus Verilog
$end
$timescale
	1ps
$end
$scope module Read_WB $end
$upscope $end
$scope module Read_weightnbais_TB $end
$var reg 16 ! t0 [15:0] $end
$var reg 16 " t1 [15:0] $end
$var reg 16 # t2 [15:0] $end
$var reg 16 $ t3 [15:0] $end
$var reg 16 % t4 [15:0] $end
$upscope $end
$enddefinitions $end
#0
$dumpvars
b0 %
b0 $
b0 #
b0 "
b0 !
$end
#1000
b11001110110110 %
b1000111111000100 $
b1011001000100111 #
b10110101100011 "
b11001100001011 !
#2000
b1010111110010011 %
b11101110111010 $
b11110000011100 #
b11100000111100 "
b1010010000011001 !
#3000
b1011000001111001 %
b1011010100000000 $
b11011100110100 #
b11100000111000 "
b1011010000010010 !
#4000
b10111101001011 %
b11000000011100 $
b1011001011101010 #
b1101010100100 "
b11001001000001 !
#5000
b1000111001011110 %
b1010111000001111 $
b10100111011001 #
b10100111001111 "
b10110000011001 !
#6000
b1010001111110010 %
b10111110000101 $
b10100101110010 #
b10110000110111 "
b1010111100100011 !
#7000
b1010100000011010 %
b1010110111011001 $
b11000011011100 #
b1010110111011000 "
b10100011111011 !
#8000
b1011000011100011 %
b11010000111101 $
b1011001111100011 #
b11000101101011 "
b1001111010011011 !
#9000
b1010100110100100 %
b10010010010010 $
b1110110001000 #
b10100000101100 "
b10100000001000 !
#10000
b1011000010101111 %
b11000000001110 $
b1011011101011101 #
b1011001100101010 "
b1010111110110010 !
#11000
b11001000100111 %
b10111100001111 $
b10101110010001 #
b11000010111101 "
b10100011001011 !
